interleave_playlist/__init__.py
interleave_playlist/__main__.py
interleave_playlist/py.typed
interleave_playlist/core/__init__.py
interleave_playlist/core/interleave.py
interleave_playlist/core/playlist.py
interleave_playlist/interface/PlaylistApplication.py
interleave_playlist/interface/PlaylistWindow.py
interleave_playlist/interface/PlaylistWindowItem.py
interleave_playlist/interface/SearchBarThread.py
interleave_playlist/interface/__init__.py
interleave_playlist/interface/style/dark.qss
interleave_playlist/model/__init__.py
interleave_playlist/persistence/__init__.py
interleave_playlist/persistence/input_.py
interleave_playlist/persistence/settings.py
interleave_playlist/persistence/state.py
interleave_playlist/persistence/watched.py
Interleave_Playlist-1.0.0a9.dist-info/LICENSE.txt
Interleave_Playlist-1.0.0a9.dist-info/METADATA
Interleave_Playlist-1.0.0a9.dist-info/WHEEL
Interleave_Playlist-1.0.0a9.dist-info/top_level.txt
Interleave_Playlist-1.0.0a9.dist-info/RECORD
