Metadata-Version: 2.2
Name: Interleave-Playlist
Version: 1.0.0a9
Author: Thomas Sweeney
License: GPL3+
Keywords: interleave,playlist,episode,show
Platform: linux
Platform: osx
Platform: unix
Platform: windows
Classifier: Development Status :: 3 - Alpha
Classifier: License :: OSI Approved :: GNU General Public License v3 or later (GPLv3+)
Classifier: Programming Language :: Python :: 3
Classifier: Programming Language :: Python :: 3 :: Only
Classifier: Programming Language :: Python :: 3.9
Classifier: Programming Language :: Python :: 3.10
Classifier: Programming Language :: Python :: 3.11
Classifier: Programming Language :: Python :: 3.12
Classifier: Programming Language :: Python :: 3.13
Classifier: Intended Audience :: End Users/Desktop
Classifier: Natural Language :: English
Requires-Python: >=3.9
License-File: LICENSE.txt
Requires-Dist: ruamel.yaml~=0.18.6
Requires-Dist: PySide6~=6.8.0
Requires-Dist: pymediainfo~=7.0.1
Requires-Dist: crontab~=1.0.1
Requires-Dist: natsort~=8.4.0
Requires-Dist: appdirs~=1.4.4
Provides-Extra: testing
Requires-Dist: pytest~=8.3.2; extra == "testing"
Requires-Dist: pytest-mock~=3.14.0; extra == "testing"
Requires-Dist: pytest-cov~=6.0.0; extra == "testing"
Requires-Dist: flake8~=7.1.1; extra == "testing"
Requires-Dist: mypy; extra == "testing"
Requires-Dist: IceSpringPySideStubs-PySide6~=1.3.1; extra == "testing"
Requires-Dist: tox~=4.24.1; extra == "testing"
Requires-Dist: freezegun~=1.5.1; extra == "testing"
Requires-Dist: pre-commit~=4.1.0; extra == "testing"
Requires-Dist: mkdocs~=1.6.0; extra == "testing"
